mb_llm/__init__.py
mb_llm/florencefile.py
mb_llm/molmo.py
mb_llm/segsam2.py
mb_llm/utils.py
mb_llm/version.py
mb_llm-1.0.85.dist-info/METADATA
mb_llm-1.0.85.dist-info/WHEEL
mb_llm-1.0.85.dist-info/top_level.txt
mb_llm-1.0.85.dist-info/RECORD
