Metadata-Version: 2.1
Name: mb_llm
Version: 1.0.85
Summary: llm tool for the MB project for Fine-tuning and Segmentation
Author: ['Malav Bateriwala']
Requires-Python: >=3.8
Requires-Dist: mb_base
